{"numero":"BR 51 2021 003063-0","titulo":"e-Bridge.Br","dataCriacao":"20/03/2021","linguagens":["FRAMEWORK"],"tiposPrograma":["AP-01","GI-01","GI-07"],"titulares":["CENTRO FEDERAL DE EDUCACAO TECNOLOGICA DE MINAS GERAIS","UNIVERSIDADE FEDERAL DE SÃO JOÃO DEL REI"],"siglasTitulares":["cefetmg"],"criadores":["ADRIANO GUIMARÃES PARREIRA","ALEXSANDRO SOBREIRA GALDINO","EDUARDO HABIB BECHELANE MAIA","JOÃO VITOR QUEIROZ","LORRAYNI MAYSSA ALVES MIGUEL","PAULO AFONSO GRANJEIRO","RAFAEL FERREIRA JAQUES","SORAIA APARECIDA ALVES"],"despachos":[{"codigo":"730","titulo":"Expedição do Certificado de Registro","rpi":"2658"}]}