{"revista":{"numero":"2518","dataPublicacao":"09/04/2019","diretoria":"Programa","despachos":[{"codigo":"111","titulo":"Despacho Anulado","processoSoftware":{"numero":"07467-6","titulo":"INFOCLINIC GESTÃO HOSPITALAR"}},{"codigo":"730","titulo":"Expedição do Certificado de Registro","processoSoftware":{"numero":"BR 51 2019 000524-4","titulo":"MATRIZ CONIF","dataCriacao":"31/12/2018"}},{"codigo":"730","titulo":"Expedição do Certificado de Registro","processoSoftware":{"numero":"BR 51 2019 000562-7","titulo":"Ponsis","dataCriacao":"19/03/2019"}},{"codigo":"730","titulo":"Expedição do Certificado de Registro","processoSoftware":{"numero":"BR 51 2019 000570-8","titulo":"BIT LABS - APLICAÇÃO PARA GERENCIAMENTO DE  LABORATÓRIO DE BROMATOLOGIA","dataCriacao":"31/12/2018"}},{"codigo":"730","titulo":"Expedição do Certificado de Registro","processoSoftware":{"numero":"BR 51 2019 000573-2","titulo":"Rede Neural","dataCriacao":"01/12/2017"}},{"codigo":"730","titulo":"Expedição do Certificado de Registro","processoSoftware":{"numero":"BR 51 2019 000574-0","titulo":"Sistema de Acompanhamento Laboratorial - AcompLab","dataCriacao":"12/02/2018"}},{"codigo":"730","titulo":"Expedição do Certificado de Registro","processoSoftware":{"numero":"BR 51 2019 000575-9","titulo":"Sistema para custeio e precificação de ensaios - Custos e Preços","dataCriacao":"14/03/2017"}},{"codigo":"730","titulo":"Expedição do Certificado de Registro","processoSoftware":{"numero":"BR 51 2019 000576-7","titulo":"ProNurse Care","dataCriacao":"06/09/2018"}},{"codigo":"730","titulo":"Expedição do Certificado de Registro","processoSoftware":{"numero":"BR 51 2019 000577-5","titulo":"NDS - Nota de Serviço","dataCriacao":"15/10/2012"}},{"codigo":"730","titulo":"Expedição do Certificado de Registro","processoSoftware":{"numero":"BR 51 2019 000578-3","titulo":"Moveonline","dataCriacao":"10/04/2018"}},{"codigo":"730","titulo":"Expedição do Certificado de Registro","processoSoftware":{"numero":"BR 51 2019 000579-1","titulo":"Inteligência artificial lógica fuzzy para efetuar controle sobre de retirada de peso corporal para treino de marcha humana","dataCriacao":"02/02/2019"}},{"codigo":"730","titulo":"Expedição do Certificado de Registro","processoSoftware":{"numero":"BR 51 2019 000580-5","titulo":"RHNydus.net","dataCriacao":"01/12/2003"}},{"codigo":"730","titulo":"Expedição do Certificado de Registro","processoSoftware":{"numero":"BR 51 2019 000581-3","titulo":"Plataforma Delfos - Versão 1.0","dataCriacao":"01/07/2018"}},{"codigo":"730","titulo":"Expedição do Certificado de Registro","processoSoftware":{"numero":"BR 51 2019 000582-1","titulo":"Primary elastic search","dataCriacao":"01/06/2018"}},{"codigo":"730","titulo":"Expedição do Certificado de Registro","processoSoftware":{"numero":"BR 51 2019 000588-0","titulo":"PLACAS E LACRES","dataCriacao":"13/12/2018"}},{"codigo":"730","titulo":"Expedição do Certificado de Registro","processoSoftware":{"numero":"BR 51 2019 000589-9","titulo":"Audiology Outcomes","dataCriacao":"15/10/2018"}},{"codigo":"730","titulo":"Expedição do Certificado de Registro","processoSoftware":{"numero":"BR 51 2019 000590-2","titulo":"MDE versão 1.0","dataCriacao":"01/10/2016"}},{"codigo":"730","titulo":"Expedição do Certificado de Registro","processoSoftware":{"numero":"BR 51 2019 000592-9","titulo":"Bentham Obras - Um Sistema Web e Mobile de Controle de Programas e Projetos de Obras","dataCriacao":"31/10/2018"}},{"codigo":"730","titulo":"Expedição do Certificado de Registro","processoSoftware":{"numero":"BR 51 2019 000593-7","titulo":"Software para captura de imagens do segmento anterior do olho humano com base na retroiluminação infravermelha","dataCriacao":"30/09/2015"}},{"codigo":"730","titulo":"Expedição do Certificado de Registro","processoSoftware":{"numero":"BR 51 2019 000594-5","titulo":"SONARA - Sistema Online de Avaliação Escolar","dataCriacao":"01/06/2018"}},{"codigo":"730","titulo":"Expedição do Certificado de Registro","processoSoftware":{"numero":"BR 51 2019 000596-1","titulo":"Simples Shop Tecnologia","dataCriacao":"02/06/2017"}},{"codigo":"730","titulo":"Expedição do Certificado de Registro","processoSoftware":{"numero":"BR 51 2019 000597-0","titulo":"Software para detecção de pupilas, recortes geométricos e estudos estatísticos de imagens obtidas por hardware proprietário equipado com iluminação infravermelha","dataCriacao":"25/06/2017"}},{"codigo":"730","titulo":"Expedição do Certificado de Registro","processoSoftware":{"numero":"BR 51 2019 000603-8","titulo":"OnePage","dataCriacao":"10/06/2018"}},{"codigo":"730","titulo":"Expedição do Certificado de Registro","processoSoftware":{"numero":"BR 51 2019 000604-6","titulo":"Aurora: Aplicativo móvel para análise da variabilidade espacial de índices de conforto térmico de animais e pessoas","dataCriacao":"01/01/2019"}},{"codigo":"730","titulo":"Expedição do Certificado de Registro","processoSoftware":{"numero":"BR 51 2019 000605-4","titulo":"CAD 2.0 Sistema de Cadastro e Gestão Escolar","dataCriacao":"01/09/2014"}},{"codigo":"730","titulo":"Expedição do Certificado de Registro","processoSoftware":{"numero":"BR 51 2019 000606-2","titulo":"MEDIAMANAGER","dataCriacao":"21/02/2008"}},{"codigo":"730","titulo":"Expedição do Certificado de Registro","processoSoftware":{"numero":"BR 51 2019 000607-0","titulo":"GCNEWS","dataCriacao":"25/08/2016"}},{"codigo":"730","titulo":"Expedição do Certificado de Registro","processoSoftware":{"numero":"BR 51 2019 000608-9","titulo":"NEOEXPRESS","dataCriacao":"17/07/2015"}},{"codigo":"730","titulo":"Expedição do Certificado de Registro","processoSoftware":{"numero":"BR 51 2019 000609-7","titulo":"NEWSMEDIA","dataCriacao":"17/02/2013"}},{"codigo":"730","titulo":"Expedição do Certificado de Registro","processoSoftware":{"numero":"BR 51 2019 000610-0","titulo":"TPNEWS","dataCriacao":"18/06/2012"}},{"codigo":"730","titulo":"Expedição do Certificado de Registro","processoSoftware":{"numero":"BR 51 2019 000611-9","titulo":"SpaceMath","dataCriacao":"16/04/2018"}},{"codigo":"730","titulo":"Expedição do Certificado de Registro","processoSoftware":{"numero":"BR 51 2019 000612-7","titulo":"CND-Morango versão 1.0","dataCriacao":"30/01/2019"}},{"codigo":"730","titulo":"Expedição do Certificado de Registro","processoSoftware":{"numero":"BR 51 2019 000613-5","titulo":"CND-Banana versão 1.0","dataCriacao":"24/07/2018"}},{"codigo":"730","titulo":"Expedição do Certificado de Registro","processoSoftware":{"numero":"BR 51 2019 000614-3","titulo":"SICOMAN web - Sistema de Controle de Manutenção","dataCriacao":"28/02/2015"}},{"codigo":"730","titulo":"Expedição do Certificado de Registro","processoSoftware":{"numero":"BR 51 2019 000615-1","titulo":"Sistema Adapter CRM para gestão de serviços de telecom, prestação de serviços e comercio em geral","dataCriacao":"01/08/2016"}},{"codigo":"730","titulo":"Expedição do Certificado de Registro","processoSoftware":{"numero":"BR 51 2019 000616-0","titulo":"CISSPoder","dataCriacao":"01/02/2000"}},{"codigo":"730","titulo":"Expedição do Certificado de Registro","processoSoftware":{"numero":"BR 51 2019 000617-8","titulo":"[11] Elleven - VDI","dataCriacao":"Não informado"}},{"codigo":"730","titulo":"Expedição do Certificado de Registro","processoSoftware":{"numero":"BR 51 2019 000618-6","titulo":"GEMFISC - Gestão Empresarial e Fiscal","dataCriacao":"01/09/2004"}},{"codigo":"730","titulo":"Expedição do Certificado de Registro","processoSoftware":{"numero":"BR 51 2019 000619-4","titulo":"Software de controle de ambiente para animais de laboratório","dataCriacao":"05/10/2018"}},{"codigo":"730","titulo":"Expedição do Certificado de Registro","processoSoftware":{"numero":"BR 51 2019 000620-8","titulo":"Controle da interface Bluetooth BTLC1000","dataCriacao":"08/02/2018"}},{"codigo":"730","titulo":"Expedição do Certificado de Registro","processoSoftware":{"numero":"BR 51 2019 000621-6","titulo":"Interface de comunicação via MQTT","dataCriacao":"21/02/2018"}},{"codigo":"730","titulo":"Expedição do Certificado de Registro","processoSoftware":{"numero":"BR 51 2019 000622-4","titulo":"Persistência de dados em memória flash","dataCriacao":"21/02/2018"}},{"codigo":"730","titulo":"Expedição do Certificado de Registro","processoSoftware":{"numero":"BR 51 2019 000623-2","titulo":"Módulo Gestor de Beacons","dataCriacao":"20/04/2018"}},{"codigo":"730","titulo":"Expedição do Certificado de Registro","processoSoftware":{"numero":"BR 51 2019 000624-0","titulo":"Configurador de módulos bluetooth","dataCriacao":"20/04/2018"}},{"codigo":"730","titulo":"Expedição do Certificado de Registro","processoSoftware":{"numero":"BR 51 2019 000625-9","titulo":"ManagerApp - Gestor de sinalização luminosa","dataCriacao":"20/04/2018"}},{"codigo":"730","titulo":"Expedição do Certificado de Registro","processoSoftware":{"numero":"BR 51 2019 000626-7","titulo":"UARTVcom - Gestor de comunicação serial","dataCriacao":"20/04/2018"}},{"codigo":"730","titulo":"Expedição do Certificado de Registro","processoSoftware":{"numero":"BR 51 2019 000627-5","titulo":"TX2CODE","dataCriacao":"01/04/2019"}},{"codigo":"730","titulo":"Expedição do Certificado de Registro","processoSoftware":{"numero":"BR 51 2019 000628-3","titulo":"ADAV - Acervo de Artes Visuais","dataCriacao":"08/03/2019"}},{"codigo":"730","titulo":"Expedição do Certificado de Registro","processoSoftware":{"numero":"BR 51 2019 000629-1","titulo":"EARVI - Exposições de Artes Visuais","dataCriacao":"08/03/2019"}},{"codigo":"730","titulo":"Expedição do Certificado de Registro","processoSoftware":{"numero":"BR 51 2019 000630-5","titulo":"JOGO 5S PARA SURDOS","dataCriacao":"14/08/2017"}},{"codigo":"730","titulo":"Expedição do Certificado de Registro","processoSoftware":{"numero":"BR 51 2019 000631-3","titulo":"FORINICIENT","dataCriacao":"23/10/2018"}},{"codigo":"730","titulo":"Expedição do Certificado de Registro","processoSoftware":{"numero":"BR 51 2019 000632-1","titulo":"FROemSA","dataCriacao":"15/10/2018"}},{"codigo":"730","titulo":"Expedição do Certificado de Registro","processoSoftware":{"numero":"BR 51 2019 000633-0","titulo":"FIREAVAEST","dataCriacao":"21/10/2018"}},{"codigo":"730","titulo":"Expedição do Certificado de Registro","processoSoftware":{"numero":"BR 51 2019 000634-8","titulo":"HEATDIFFUSION1D","dataCriacao":"29/08/2018"}},{"codigo":"730","titulo":"Expedição do Certificado de Registro","processoSoftware":{"numero":"BR 51 2019 000635-6","titulo":"REQATICO","dataCriacao":"05/10/2018"}},{"codigo":"730","titulo":"Expedição do Certificado de Registro","processoSoftware":{"numero":"BR 51 2019 000636-4","titulo":"LNATCDSmartSchool","dataCriacao":"11/04/2018"}},{"codigo":"730","titulo":"Expedição do Certificado de Registro","processoSoftware":{"numero":"BR 51 2019 000637-2","titulo":"Organizeve","dataCriacao":"17/10/2018"}},{"codigo":"730","titulo":"Expedição do Certificado de Registro","processoSoftware":{"numero":"BR 51 2019 000638-0","titulo":"LBIOMICDB - Sistema de Gerenciamento de Dados Biológicos para Coleções de Micro-organismos","dataCriacao":"10/12/2018"}},{"codigo":"730","titulo":"Expedição do Certificado de Registro","processoSoftware":{"numero":"BR 51 2019 000639-9","titulo":"PRESUCE","dataCriacao":"03/11/2018"}},{"codigo":"730","titulo":"Expedição do Certificado de Registro","processoSoftware":{"numero":"BR 51 2019 000640-2","titulo":"FREQ-EXTENSÃO","dataCriacao":"18/10/2018"}},{"codigo":"730","titulo":"Expedição do Certificado de Registro","processoSoftware":{"numero":"BR 51 2019 000641-0","titulo":"NAVIERSTOKES2DFLOW","dataCriacao":"05/10/2018"}},{"codigo":"730","titulo":"Expedição do Certificado de Registro","processoSoftware":{"numero":"BR 51 2019 000642-9","titulo":"ALT_ESTAGIO","dataCriacao":"15/09/2018"}},{"codigo":"730","titulo":"Expedição do Certificado de Registro","processoSoftware":{"numero":"BR 51 2019 000643-7","titulo":"FORVISITEC","dataCriacao":"07/10/2018"}},{"codigo":"730","titulo":"Expedição do Certificado de Registro","processoSoftware":{"numero":"BR 51 2019 000644-5","titulo":"DEC_EVENTOS","dataCriacao":"18/10/2018"}},{"codigo":"730","titulo":"Expedição do Certificado de Registro","processoSoftware":{"numero":"BR 51 2019 000645-3","titulo":"LecturePlanTeX","dataCriacao":"15/03/2018"}},{"codigo":"730","titulo":"Expedição do Certificado de Registro","processoSoftware":{"numero":"BR 51 2019 000646-1","titulo":"ATVCOMPLEM","dataCriacao":"07/09/2018"}},{"codigo":"730","titulo":"Expedição do Certificado de Registro","processoSoftware":{"numero":"BR 51 2019 000647-0","titulo":"FIROTEVIDEO","dataCriacao":"05/09/2018"}},{"codigo":"730","titulo":"Expedição do Certificado de Registro","processoSoftware":{"numero":"BR 51 2019 000648-8","titulo":"TP Knowledge","dataCriacao":"30/05/2018"}},{"codigo":"730","titulo":"Expedição do Certificado de Registro","processoSoftware":{"numero":"BR 51 2019 000649-6","titulo":"Plataforma Gestão por Eficiência (I3)","dataCriacao":"Não informado"}},{"codigo":"730","titulo":"Expedição do Certificado de Registro","processoSoftware":{"numero":"BR 51 2019 000650-0","titulo":"PROTÓTIPO DE APLICATIVO MÓVEL PARA UM SISTEMA DE INFORMAÇÃO PARA ASSISTÊNCIA SOCIAL","dataCriacao":"23/10/2018"}},{"codigo":"730","titulo":"Expedição do Certificado de Registro","processoSoftware":{"numero":"BR 51 2019 000651-8","titulo":"MINIJOB","dataCriacao":"02/08/2016"}},{"codigo":"730","titulo":"Expedição do Certificado de Registro","processoSoftware":{"numero":"BR 51 2019 000652-6","titulo":"Painel Abertura Simples","dataCriacao":"12/06/2018"}},{"codigo":"730","titulo":"Expedição do Certificado de Registro","processoSoftware":{"numero":"BR 51 2019 000654-2","titulo":"CoNuMitAC - Contagem de Núcleos nas Fases da Mitose em Lâminas de Allium cepa","dataCriacao":"05/11/2018"}},{"codigo":"730","titulo":"Expedição do Certificado de Registro","processoSoftware":{"numero":"BR 51 2019 000656-9","titulo":"Ondemand Network","dataCriacao":"12/11/2013"}},{"codigo":"730","titulo":"Expedição do Certificado de Registro","processoSoftware":{"numero":"BR 51 2019 000657-7","titulo":"RPN - REPOSITÓRIO DE PROCESSOS DE NEGÓCIOS","dataCriacao":"01/12/2018"}},{"codigo":"732","titulo":"Alteração de Razão Social","processoSoftware":{"numero":"BR 51 2019 000540-6","titulo":"Fleet Expert"}},{"codigo":"732","titulo":"Alteração de Razão Social","processoSoftware":{"numero":"BR 51 2019 000543-0","titulo":"Fleet Expert ENERGIA"}},{"codigo":"733","titulo":"Alteração de endereço","processoSoftware":{"numero":"BR 51 2019 000543-0","titulo":"Fleet Expert ENERGIA"}},{"codigo":"734","titulo":"Transferência de Titularidade","processoSoftware":{"numero":"07467-6","titulo":"INFOCLINIC GESTÃO HOSPITALAR"}},{"codigo":"734","titulo":"Transferência de Titularidade","processoSoftware":{"numero":"BR 51 2019 000424-8","titulo":"BIDDER"}},{"codigo":"742","titulo":"Petição não conhecida","processoSoftware":{"numero":"BR 51 2019 000503-1","titulo":"Aplicativo silhueta"}},{"codigo":"742","titulo":"Petição não conhecida","processoSoftware":{"numero":"BR 51 2019 000507-4","titulo":"OUVIDORIA - MÓDULO ACOMPANHADO DE BI"}},{"codigo":"742","titulo":"Petição não conhecida","processoSoftware":{"numero":"BR 51 2019 000533-3","titulo":"sqlBASE-for-DB2"}},{"codigo":"742","titulo":"Petição não conhecida","processoSoftware":{"numero":"BR 51 2019 000583-0","titulo":"Planoaula"}},{"codigo":"742","titulo":"Petição não conhecida","processoSoftware":{"numero":"BR 51 2019 000584-8","titulo":"PLADEUNI"}},{"codigo":"742","titulo":"Petição não conhecida","processoSoftware":{"numero":"BR 51 2019 000585-6","titulo":"PLANEINTER"}},{"codigo":"742","titulo":"Petição não conhecida","processoSoftware":{"numero":"BR 51 2019 000586-4","titulo":"MDFMEFcomTDMA"}},{"codigo":"742","titulo":"Petição não conhecida","processoSoftware":{"numero":"BR 51 2019 000587-2","titulo":"DECLACOAU"}},{"codigo":"742","titulo":"Petição não conhecida","processoSoftware":{"numero":"BR 51 2019 000595-3","titulo":"FORORGCUES"}},{"codigo":"742","titulo":"Petição não conhecida","processoSoftware":{"numero":"BR 51 2019 000598-8","titulo":"DecCop-Autenticas"}},{"codigo":"742","titulo":"Petição não conhecida","processoSoftware":{"numero":"BR 51 2019 000599-6","titulo":"PERMLINERARTHERMOELAST1D"}},{"codigo":"742","titulo":"Petição não conhecida","processoSoftware":{"numero":"BR 51 2019 000600-3","titulo":"SESweetHome"}},{"codigo":"742","titulo":"Petição não conhecida","processoSoftware":{"numero":"BR 51 2019 000601-1","titulo":"LNATRLSmartSchool"}},{"codigo":"742","titulo":"Petição não conhecida","processoSoftware":{"numero":"BR 51 2019 000602-0","titulo":"HEATCONVENTION2D"}},{"codigo":"747","titulo":"Correção de dados no Certificado de Registro devido à falha do interessado","processoSoftware":{"numero":"BR 51 2019 000241-5","titulo":"E WATS - ELECTRIC  WHEELCHAIR ASSESSMENT AND TRAINING SIMULATOR"}},{"codigo":"747","titulo":"Correção de dados no Certificado de Registro devido à falha do interessado","processoSoftware":{"numero":"BR 51 2019 000552-0","titulo":"SEVEN SYSTEM"}},{"codigo":"747","titulo":"Correção de dados no Certificado de Registro devido à falha do interessado","processoSoftware":{"numero":"BR 51 2019 000553-8","titulo":"SEVEN SYSTEM"}}]}}