{"revista":{"numero":"2662","dataPublicacao":"11/01/2022","diretoria":"Programa","despachos":[{"codigo":"111","titulo":"Despacho Anulado","processoSoftware":{"numero":"BR 51 2021 003188-1","titulo":"Biblioteca Arduino para o Protocolo AMASP"}},{"codigo":"730","titulo":"Expedição do Certificado de Registro","processoSoftware":{"numero":"BR 51 2021 003188-1","titulo":"Biblioteca Arduino para o Protocolo AMASP","dataCriacao":"13/12/2020"}},{"codigo":"730","titulo":"Expedição do Certificado de Registro","processoSoftware":{"numero":"BR 51 2021 003250-0","titulo":"Smart Dryer - Software Embarcado","dataCriacao":"20/12/2021"}},{"codigo":"730","titulo":"Expedição do Certificado de Registro","processoSoftware":{"numero":"BR 51 2021 003254-3","titulo":"SB FÁCIL","dataCriacao":"10/01/2007"}},{"codigo":"730","titulo":"Expedição do Certificado de Registro","processoSoftware":{"numero":"BR 51 2022 000001-6","titulo":"Zetta Journey","dataCriacao":"15/07/2021"}},{"codigo":"730","titulo":"Expedição do Certificado de Registro","processoSoftware":{"numero":"BR 51 2022 000002-4","titulo":"GMSISTEMAS","dataCriacao":"01/01/2016"}},{"codigo":"730","titulo":"Expedição do Certificado de Registro","processoSoftware":{"numero":"BR 51 2022 000003-2","titulo":"Plataforma Neema - Neural and Emotional Environment for Mixed Applications - Ambiente Neural e Emocional para Aplicações Mistas.","dataCriacao":"Não informado"}},{"codigo":"730","titulo":"Expedição do Certificado de Registro","processoSoftware":{"numero":"BR 51 2022 000004-0","titulo":"Lancet","dataCriacao":"19/04/2004"}},{"codigo":"730","titulo":"Expedição do Certificado de Registro","processoSoftware":{"numero":"BR 51 2022 000005-9","titulo":"ENDO PÓS","dataCriacao":"06/12/2021"}},{"codigo":"730","titulo":"Expedição do Certificado de Registro","processoSoftware":{"numero":"BR 51 2022 000006-7","titulo":"Misc: Aplicativo para Monitoramento de Infecções de Pacientes Cirúrgicos","dataCriacao":"03/11/2020"}},{"codigo":"730","titulo":"Expedição do Certificado de Registro","processoSoftware":{"numero":"BR 51 2022 000007-5","titulo":"FlashplayHR","dataCriacao":"23/08/2021"}},{"codigo":"730","titulo":"Expedição do Certificado de Registro","processoSoftware":{"numero":"BR 51 2022 000008-3","titulo":"Wakeme - Captação de Alunos","dataCriacao":"12/08/2015"}},{"codigo":"730","titulo":"Expedição do Certificado de Registro","processoSoftware":{"numero":"BR 51 2022 000009-1","titulo":"Susy Alô Saúde","dataCriacao":"15/10/2021"}},{"codigo":"730","titulo":"Expedição do Certificado de Registro","processoSoftware":{"numero":"BR 51 2022 000010-5","titulo":"AgDataBox - Sensor","dataCriacao":"01/07/2019"}},{"codigo":"730","titulo":"Expedição do Certificado de Registro","processoSoftware":{"numero":"BR 51 2022 000011-3","titulo":"Sistema de Contabilidade e Folha de Pagamento","dataCriacao":"30/10/2019"}},{"codigo":"730","titulo":"Expedição do Certificado de Registro","processoSoftware":{"numero":"BR 51 2022 000012-1","titulo":"Painel de Leitos","dataCriacao":"30/10/2019"}},{"codigo":"730","titulo":"Expedição do Certificado de Registro","processoSoftware":{"numero":"BR 51 2022 000013-0","titulo":"Sistema Ambulatorial e Hospitalar","dataCriacao":"30/10/2019"}},{"codigo":"730","titulo":"Expedição do Certificado de Registro","processoSoftware":{"numero":"BR 51 2022 000014-8","titulo":"From-To - Integração de Dados","dataCriacao":"13/06/2019"}},{"codigo":"730","titulo":"Expedição do Certificado de Registro","processoSoftware":{"numero":"BR 51 2022 000015-6","titulo":"Programa para análise de respostas em questões de múltipla escolha","dataCriacao":"15/11/2021"}},{"codigo":"730","titulo":"Expedição do Certificado de Registro","processoSoftware":{"numero":"BR 51 2022 000016-4","titulo":"SPGU - SISTEMA DE PLANEJAMENTO E GESTÃO UNIVERSITÁRIA","dataCriacao":"17/03/2017"}},{"codigo":"730","titulo":"Expedição do Certificado de Registro","processoSoftware":{"numero":"BR 51 2022 000017-2","titulo":"SIMULLA CRESAC","dataCriacao":"24/11/2021"}},{"codigo":"730","titulo":"Expedição do Certificado de Registro","processoSoftware":{"numero":"BR 51 2022 000018-0","titulo":"BEMPlateChanfrMind","dataCriacao":"01/12/2021"}},{"codigo":"730","titulo":"Expedição do Certificado de Registro","processoSoftware":{"numero":"BR 51 2022 000019-9","titulo":"NP FÁCIL","dataCriacao":"30/08/2021"}},{"codigo":"730","titulo":"Expedição do Certificado de Registro","processoSoftware":{"numero":"BR 51 2022 000020-2","titulo":"CAJUPE","dataCriacao":"05/09/2018"}},{"codigo":"730","titulo":"Expedição do Certificado de Registro","processoSoftware":{"numero":"BR 51 2022 000021-0","titulo":"Software para análise multidimensional em Sistemas Aquosos Bifásicos-SAMSAB","dataCriacao":"17/11/2020"}},{"codigo":"730","titulo":"Expedição do Certificado de Registro","processoSoftware":{"numero":"BR 51 2022 000022-9","titulo":"Cerurb - Tecnologia Fundiária","dataCriacao":"02/01/2021"}},{"codigo":"730","titulo":"Expedição do Certificado de Registro","processoSoftware":{"numero":"BR 51 2022 000023-7","titulo":"Guru de Seguros","dataCriacao":"10/11/2021"}},{"codigo":"730","titulo":"Expedição do Certificado de Registro","processoSoftware":{"numero":"BR 51 2022 000024-5","titulo":"Agro SEEN","dataCriacao":"05/01/2022"}},{"codigo":"730","titulo":"Expedição do Certificado de Registro","processoSoftware":{"numero":"BR 51 2022 000025-3","titulo":"CCS - CENTRAL CONTROL SYSTEM","dataCriacao":"01/02/2021"}},{"codigo":"730","titulo":"Expedição do Certificado de Registro","processoSoftware":{"numero":"BR 51 2022 000026-1","titulo":"BOXHUB","dataCriacao":"10/12/2021"}},{"codigo":"730","titulo":"Expedição do Certificado de Registro","processoSoftware":{"numero":"BR 51 2022 000027-0","titulo":"SYCONI MENSAGENS INSTANTÂNEAS","dataCriacao":"01/09/2021"}},{"codigo":"730","titulo":"Expedição do Certificado de Registro","processoSoftware":{"numero":"BR 51 2022 000028-8","titulo":"ARES","dataCriacao":"09/08/2021"}},{"codigo":"730","titulo":"Expedição do Certificado de Registro","processoSoftware":{"numero":"BR 51 2022 000029-6","titulo":"Aplicativo de Autoavaliação MDE-S","dataCriacao":"02/02/2020"}},{"codigo":"730","titulo":"Expedição do Certificado de Registro","processoSoftware":{"numero":"BR 51 2022 000030-0","titulo":"NutriAção de Bolso - v2.0","dataCriacao":"03/12/2021"}},{"codigo":"730","titulo":"Expedição do Certificado de Registro","processoSoftware":{"numero":"BR 51 2022 000031-8","titulo":"JOGOEduc2022: Caça Palavras no Bicentenário da Independência do Brasil","dataCriacao":"05/06/2021"}},{"codigo":"730","titulo":"Expedição do Certificado de Registro","processoSoftware":{"numero":"BR 51 2022 000032-6","titulo":"Cardian 3.2.0","dataCriacao":"22/06/2021"}},{"codigo":"730","titulo":"Expedição do Certificado de Registro","processoSoftware":{"numero":"BR 51 2022 000033-4","titulo":"Geneticae Optmius Cibus -  A Metaheuristic for Scheduling Problems","dataCriacao":"06/01/2022"}},{"codigo":"730","titulo":"Expedição do Certificado de Registro","processoSoftware":{"numero":"BR 51 2022 000034-2","titulo":"OVINOCAPRI medicamentos e vacinações","dataCriacao":"05/12/2021"}},{"codigo":"730","titulo":"Expedição do Certificado de Registro","processoSoftware":{"numero":"BR 51 2022 000035-0","titulo":"Navigator","dataCriacao":"03/01/2020"}},{"codigo":"730","titulo":"Expedição do Certificado de Registro","processoSoftware":{"numero":"BR 51 2022 000036-9","titulo":"Navigator","dataCriacao":"03/01/2020"}},{"codigo":"730","titulo":"Expedição do Certificado de Registro","processoSoftware":{"numero":"BR 51 2022 000037-7","titulo":"Stress Lipp App","dataCriacao":"01/05/2021"}},{"codigo":"730","titulo":"Expedição do Certificado de Registro","processoSoftware":{"numero":"BR 51 2022 000038-5","titulo":"Automação de rotinas e processos para Corretores de Seguros","dataCriacao":"25/10/2021"}},{"codigo":"730","titulo":"Expedição do Certificado de Registro","processoSoftware":{"numero":"BR 51 2022 000040-7","titulo":"gestão de demandas e emissão de seguros garantia e evolução para outros ramos","dataCriacao":"28/12/2021"}},{"codigo":"730","titulo":"Expedição do Certificado de Registro","processoSoftware":{"numero":"BR 51 2022 000042-3","titulo":"ESTOMATOGAME","dataCriacao":"17/11/2021"}},{"codigo":"730","titulo":"Expedição do Certificado de Registro","processoSoftware":{"numero":"BR 51 2022 000043-1","titulo":"Aplicativo Mobile para Cálculo de Resistência Elétrica","dataCriacao":"01/12/2021"}},{"codigo":"734","titulo":"Transferência de Titularidade","processoSoftware":{"numero":"14080-1","titulo":"KEA TECH"}},{"codigo":"734","titulo":"Transferência de Titularidade","processoSoftware":{"numero":"BR 51 2016 001068-1","titulo":"SIP"}},{"codigo":"734","titulo":"Transferência de Titularidade","processoSoftware":{"numero":"BR 51 2019 001654-8","titulo":"Sistema de Gestão de compras"}},{"codigo":"742","titulo":"Petição não conhecida","processoSoftware":{"numero":"BR 51 2018 051632-7","titulo":"Sistema Faculdade"}},{"codigo":"742","titulo":"Petição não conhecida","processoSoftware":{"numero":"BR 51 2021 003188-1","titulo":"Biblioteca Arduino para o Protocolo AMASP"}},{"codigo":"747","titulo":"Correção de dados no Certificado de Registro devido à falha do interessado","processoSoftware":{"numero":"BR 51 2021 002823-6","titulo":"PAS 1.07"}}]}}