{"numero":"BR 11 2023 023601-0","pedidoInternacional":{"numeroPCT":"PCT FR2022/050892","dataPCT":"10/05/2022"},"publicacaoInternacional":{"numeroOMPI":"WO 2022/238653","dataOMPI":"17/11/2022"},"IPC":["B64D 27/24","B64C 27/12","B64D 35/00","B64D 31/00","B64D 27/02"],"prioridadesUnionistas":[{"siglaPais":"FR","numeroPrioridade":"FR2104948","dataPrioridade":"10/05/2021"}],"despachos":[{"codigo":"1.1","titulo":"Pedido Internacional PCT Publicado. Petição de Requerimento de Entrada na Fase Nacional Recebida","rpi":"2759"}]}