{"numero":"BR 11 2023 011792-5","pedidoInternacional":{"numeroPCT":"PCT GB2021/053332","dataPCT":"16/12/2021"},"publicacaoInternacional":{"numeroOMPI":"WO 2022/129925","dataOMPI":"23/06/2022"},"IPC":["C07D 277/10","C07D 417/06","A61K 31/426","A61P 9/00","A61P 25/00","A61P 35/00"],"prioridadesUnionistas":[{"siglaPais":"GB","numeroPrioridade":"2020186.9","dataPrioridade":"18/12/2020"},{"siglaPais":"GB","numeroPrioridade":"2102494.8","dataPrioridade":"22/02/2021"}],"despachos":[{"codigo":"1.1","titulo":"Publicação Internacional – PCT. Apresentação de petição de requerimento de entrada na fase nacional","rpi":"2738"}]}