{"numero":"BR 11 2021 002948-6","pedidoInternacional":{"numeroPCT":"PCT US2018/047288","dataPCT":"21/08/2018"},"publicacaoInternacional":{"numeroOMPI":"WO 2020/040746","dataOMPI":"27/02/2020"},"IPC":["B64C 25/48"],"despachos":[{"codigo":"1.1","titulo":"Publicação Internacional – PCT. Apresentação de petição de requerimento de entrada na fase nacional","rpi":"2617"},{"codigo":"1.3","titulo":"Notificação - Fase Nacional - PCT","rpi":"2627"},{"codigo":"6.23","titulo":"Exigência preliminar - pedidos com buscas realizadas por outros Escritórios de Patentes","rpi":"2700"}],"dataDeposito":"21/08/2018","dataFaseNacional":"18/02/2021","titulo":"SISTEMA E ALGORITMO DE REALIMENTAÇÃO DE DESACELERAÇÃO","titulares":[{"nomeCompleto":"MEGGITT AIRCRAFT BRAKING SYSTEMS CORPORATION","pais":"US"}],"inventores":["ANDREW WHITTINGHAM"]}