{"numero":"BR 11 2023 018152-6","pedidoInternacional":{"numeroPCT":"PCT US2022/019252","dataPCT":"08/03/2022"},"publicacaoInternacional":{"numeroOMPI":"WO 2022/192186","dataOMPI":"15/09/2022"},"IPC":["C12N 15/10","C12N 9/22","C40B 40/08"],"prioridadesUnionistas":[{"siglaPais":"US","numeroPrioridade":"63/158,492","dataPrioridade":"09/03/2021"},{"siglaPais":"US","numeroPrioridade":"63/162,775","dataPrioridade":"18/03/2021"},{"siglaPais":"US","numeroPrioridade":"63/163,381","dataPrioridade":"19/03/2021"},{"siglaPais":"US","numeroPrioridade":"63/228,344","dataPrioridade":"02/08/2021"},{"siglaPais":"US","numeroPrioridade":"63/246,879","dataPrioridade":"22/09/2021"},{"siglaPais":"US","numeroPrioridade":"63/295,432","dataPrioridade":"30/12/2021"}],"despachos":[{"codigo":"1.1","titulo":"Publicação Internacional – PCT. Apresentação de petição de requerimento de entrada na fase nacional","rpi":"2750"}]}