{"numero":"BR 11 2023 022534-5","pedidoInternacional":{"numeroPCT":"PCT EP2021/080300","dataPCT":"02/11/2021"},"publicacaoInternacional":{"numeroOMPI":"WO 2022/228706","dataOMPI":"03/11/2022"},"IPC":["A61K 39/395","A61K 38/17","A61P 35/00","A61K 31/675","A61K 31/704"],"prioridadesUnionistas":[{"siglaPais":"US","numeroPrioridade":"63/182,398","dataPrioridade":"30/04/2021"},{"siglaPais":"US","numeroPrioridade":"63/226,962","dataPrioridade":"29/07/2021"}],"despachos":[{"codigo":"1.1","titulo":"Pedido Internacional PCT Publicado. Petição de Requerimento de Entrada na Fase Nacional Recebida","rpi":"2757"}]}