{"numero":"BR 11 2023 014436-1","pedidoInternacional":{"numeroPCT":"PCT US2022/012935","dataPCT":"19/01/2022"},"publicacaoInternacional":{"numeroOMPI":"WO 2022/159460","dataOMPI":"28/07/2022"},"IPC":["C12N 5/0781","C12N 5/0784","C12N 5/0786"],"prioridadesUnionistas":[{"siglaPais":"US","numeroPrioridade":"63/139,680","dataPrioridade":"20/01/2021"}],"despachos":[{"codigo":"1.1","titulo":"Publicação Internacional – PCT. Apresentação de petição de requerimento de entrada na fase nacional","rpi":"2742"}]}