{"numero":"BR 11 2023 026808-7","pedidoInternacional":{"numeroPCT":"PCT EP2022/065787","dataPCT":"10/06/2022"},"publicacaoInternacional":{"numeroOMPI":"WO 2022/268525","dataOMPI":"29/12/2022"},"IPC":["C07B 31/00","C07D 307/44","C07F 9/50","C07F 13/00","C07D 307/92","C07C 29/149"],"prioridadesUnionistas":[{"siglaPais":"EP","numeroPrioridade":"21180529.6","dataPrioridade":"21/06/2021"}],"despachos":[{"codigo":"1.1","titulo":"Pedido Internacional PCT Publicado. Petição de Requerimento de Entrada na Fase Nacional Recebida","rpi":"2764"}]}