{"numero":"BR 10 2018 007528-4","dataDeposito":"13/04/2018","titulares":[{"nomeCompleto":"MACHADO EQUIPAMENTOS RODOVIÁRIOS LTDA.","uf":"SP","pais":"BR"}],"despachos":[{"codigo":"2.1","titulo":"Pedido de Patente ou Certificado de Adição de Invenção depositado","rpi":"2488"},{"codigo":"3.2","titulo":"Publicação Antecipada","rpi":"2502"},{"codigo":"28.10.22","titulo":"Notificação de requerimento de trâmite prioritário de terceiro acusado de contrafação","rpi":"2750"},{"codigo":"28.30","titulo":"Trâmite prioritário admitido","rpi":"2751"},{"codigo":"7.1","titulo":"Conhecimento de Parecer Técnico","rpi":"2764"}],"titulo":"DISPOSIÇÃO CONSTRUTIVA EM PONTEIRA PIVOTADA DE EIXO AUXILIAR VEICULAR COM PINO MESTRE CÔNICO, PARA MONTAGEM E DESMONTAGEM DO CONJUNTO DE PIVOTAGEM","IPC":["B62D 13/00","B60G 7/00"],"inventores":["PAULO FERREIRA MACHADO"]}