{"numero":"BR 12 2023 011961-4","dataDeposito":"28/01/2016","titulares":[{"nomeCompleto":"ILTEC - LUBECK TECNOLOGIA LTDA.","uf":"SP","pais":"BR"}],"divisaoPedido":{"dataDeposito":"28/01/2016","numero":"BR 10 2016 001959-1"},"despachos":[{"codigo":"2.10","titulo":"Requerimento de Pedido de Patente ou Certificado de Adição de Invenção","rpi":"2738"},{"codigo":"2.4","titulo":"Pedido dividido depositado - Art 26 inciso I da LPI","rpi":"2751"},{"codigo":"28.10.32","titulo":"Notificação de requerimento de trâmite prioritário de PPH","rpi":"2761"},{"codigo":"28.30","titulo":"Trâmite prioritário admitido","rpi":"2762"}]}