{"numero":"BR 10 2017 002195-5","dataDeposito":"02/02/2017","titulo":"APERFEIÇOAMENTOS INTRODUZIDOS EM MECANISMO DE VEDAÇÃO CERÂMICO PARA REGISTROS E TORNEIRAS DE PRESSÃO","IPC":["F16K 5/04","F16K 5/08","F16K 5/14","F16K 27/06","F16K 41/00","F16J 15/16"],"titulares":[{"nomeCompleto":"BLUKIT METALÚRGICA LTDA","uf":"SC","pais":"BR"}],"inventores":["ADRIAN ROGERS CENSI"],"despachos":[{"codigo":"3.1","titulo":"Publicação do Pedido de Patente ou de Certificado de Adição de Invenção","rpi":"2485"},{"codigo":"7.1","titulo":"Conhecimento de Parecer Técnico","rpi":"2763"}]}