{"numero":"PI 0810658-4","dataDeposito":"18/04/2008","IPC":["C12N 9/00","C07K 14/415","C12N 15/82","A01H 5/00"],"titulares":[{"nomeCompleto":"Monsanto Technology LLC","pais":"US"}],"despachos":[{"codigo":"6.21","titulo":"Exigência preliminar - pedidos com buscas realizadas por outros Escritórios de Patentes","rpi":"2585"},{"codigo":"6.1","titulo":"Exigência Técnica","rpi":"2599"},{"codigo":"9.2","titulo":"Indeferimento","rpi":"2616"},{"codigo":"12.2","titulo":"Recurso Contra o Indeferimento","rpi":"2626"},{"codigo":"100","titulo":"Recurso conhecido e provido. Reformada a Decisão recorrida e deferido o pedido","rpi":"2743"}],"titulo":"PLANTAS E SEMENTE DE MILHO COM TEOR AUMENTADO DE ASPARAGINA E PROTEÍNA."}