{"numero":"PI 9903509-0","dataDeposito":"03/08/1999","dataConcessao":"08/10/2013","titulo":"Composição de atração, armadilhamento e/ou extermínio do percevejo da soja Piezodorus guildinii","IPC":["A01N 63/00"],"titulares":[{"nomeCompleto":"Embrapa - Empresa Brasileira de Pesquisa Agropecuária","uf":"DF","pais":"BR"}],"inventores":["Miguel Borges","EDISON RYOITI SUJII","Maria Luiza Marcico Publio de Castro","Paulo Henrique Gorgatti Zarbin"],"despachos":[{"codigo":"16.3","titulo":"Retificação","rpi":"2590"}]}